main.py
dxt-0.0.1.dist-info/METADATA
dxt-0.0.1.dist-info/WHEEL
dxt-0.0.1.dist-info/top_level.txt
dxt-0.0.1.dist-info/RECORD
