Metadata-Version: 2.1
Name: dxt
Version: 0.0.1
Summary: dxt
Author: 4sushi
License: MIT
Keywords: dxt
Platform: UNKNOWN
Classifier: Programming Language :: Python :: 3
Classifier: License :: OSI Approved :: MIT License
Classifier: Operating System :: OS Independent
Requires-Python: >=3.7
